examples/README.md
examples/basic_usage.py
examples/dielectric_parameter_study.png
examples/eigenmode_analysis.py
examples/frequency_domain_simulation.py
examples/palace_tutorial.ipynb
examples/time_domain_simulation.py
palace/__init__.py
palace/cli.py
palace/core.py
palace/utils.py
palace_fem-0.1.0.dist-info/licenses/LICENSE
palace_fem-0.1.0.dist-info/licenses/NOTICE
tests/README.md
tests/__init__.py
tests/conftest.py
tests/test_runner.py
tests/integration/test_examples.py
tests/unit/test_core.py
tests/unit/test_utils.py
palace_fem-0.1.0.dist-info/METADATA
palace_fem-0.1.0.dist-info/WHEEL
palace_fem-0.1.0.dist-info/entry_points.txt
palace_fem-0.1.0.dist-info/top_level.txt
palace_fem-0.1.0.dist-info/RECORD
