Metadata-Version: 2.4
Name: palace-fem
Version: 0.1.0
Summary: 3D Finite Element Solver for Computational Electromagnetics
Home-page: https://github.com/awslabs/palace
Author: AWS Center for Quantum Computing
Author-email: AWS Center for Quantum Computing <palace-maint@amazon.com>
Maintainer-email: AWS Center for Quantum Computing <palace-maint@amazon.com>
License: Apache-2.0
Project-URL: Bug Tracker, https://github.com/awslabs/palace/issues
Project-URL: Documentation, https://awslabs.github.io/palace/
Project-URL: Homepage, https://github.com/awslabs/palace
Project-URL: Repository, https://github.com/awslabs/palace
Keywords: finite element,electromagnetics,simulation,physics
Classifier: Development Status :: 4 - Beta
Classifier: Intended Audience :: Science/Research
Classifier: Intended Audience :: Developers
Classifier: License :: OSI Approved :: Apache Software License
Classifier: Operating System :: OS Independent
Classifier: Programming Language :: Python :: 3
Classifier: Programming Language :: Python :: 3.8
Classifier: Programming Language :: Python :: 3.9
Classifier: Programming Language :: Python :: 3.10
Classifier: Programming Language :: Python :: 3.11
Classifier: Programming Language :: Python :: 3.12
Classifier: Topic :: Scientific/Engineering
Classifier: Topic :: Scientific/Engineering :: Mathematics
Classifier: Topic :: Scientific/Engineering :: Physics
Requires-Python: >=3.8
License-File: LICENSE
License-File: NOTICE
Requires-Dist: numpy>=1.20.0
Requires-Dist: scipy>=1.7.0
Provides-Extra: dev
Requires-Dist: pytest>=6.0; extra == "dev"
Requires-Dist: pytest-cov; extra == "dev"
Requires-Dist: ruff; extra == "dev"
Requires-Dist: mypy; extra == "dev"
Provides-Extra: docs
Requires-Dist: sphinx>=4.0; extra == "docs"
Requires-Dist: sphinx-rtd-theme; extra == "docs"
Requires-Dist: myst-parser; extra == "docs"
Provides-Extra: visualization
Requires-Dist: matplotlib>=3.3.0; extra == "visualization"
Requires-Dist: paraview>=5.9.0; extra == "visualization"
Dynamic: author
Dynamic: home-page
Dynamic: license-file
Dynamic: requires-python
